arrow_cache/__init__.py
arrow_cache/cache.py
arrow_cache/cache_entry.py
arrow_cache/config.py
arrow_cache/converters.py
arrow_cache/eviction_policy.py
arrow_cache/memory.py
arrow_cache/metadata_store.py
arrow_cache/partitioning.py
arrow_cache/query_optimization.py
arrow_cache/threading.py
arrow_cache/utils.py
arrow_cache-0.2.1.dist-info/METADATA
arrow_cache-0.2.1.dist-info/WHEEL
arrow_cache-0.2.1.dist-info/entry_points.txt
arrow_cache-0.2.1.dist-info/top_level.txt
arrow_cache-0.2.1.dist-info/RECORD
